pyfilename/__init__.py
pyfilename/main.py
pyfilename-0.6.0.post1.dist-info/METADATA
pyfilename-0.6.0.post1.dist-info/WHEEL
pyfilename-0.6.0.post1.dist-info/licenses/LICENSE
pyfilename-0.6.0.post1.dist-info/RECORD
