Metadata-Version: 2.3
Name: pyfilename
Version: 0.6.0.post1
Summary: Make names comply various filename constraints of Windows.
Project-URL: Repository, https://github.com/ilotoki0804/pyfilename
Project-URL: Funding, https://github.com/sponsors/ilotoki0804
Author-email: ilotoki0804 <ilotoki0804@gmail.com>
License-Expression: MIT
License-File: LICENSE
Keywords: file,files,windows
Classifier: License :: OSI Approved :: MIT License
Classifier: Operating System :: OS Independent
Classifier: Programming Language :: Python :: 3.9
Classifier: Programming Language :: Python :: 3.10
Classifier: Programming Language :: Python :: 3.11
Classifier: Programming Language :: Python :: 3.12
Classifier: Programming Language :: Python :: 3.13
Requires-Python: >=3.9
